ConglingkaishiDeUefiLuojiBiancheng/README.md
ConglingkaishiDeUefiLuojiBiancheng/__init__.py
ConglingkaishiDeUefiLuojiBiancheng/__main__.py
ConglingkaishiDeUefiLuojiBiancheng/file.epub
ConglingkaishiDeUefiLuojiBiancheng/index.html
ConglingkaishiDeUefiLuojiBiancheng/css/__init__.py
ConglingkaishiDeUefiLuojiBiancheng/css/annotations.css
ConglingkaishiDeUefiLuojiBiancheng/css/main.css
ConglingkaishiDeUefiLuojiBiancheng/css/normalize.css
ConglingkaishiDeUefiLuojiBiancheng/css/popup.css
ConglingkaishiDeUefiLuojiBiancheng/font/__init__.py
ConglingkaishiDeUefiLuojiBiancheng/font/fontello.eot
ConglingkaishiDeUefiLuojiBiancheng/font/fontello.svg
ConglingkaishiDeUefiLuojiBiancheng/font/fontello.ttf
ConglingkaishiDeUefiLuojiBiancheng/font/fontello.woff
ConglingkaishiDeUefiLuojiBiancheng/img/__init__.py
ConglingkaishiDeUefiLuojiBiancheng/img/annotator-glyph-sprite.png
ConglingkaishiDeUefiLuojiBiancheng/img/annotator-icon-sprite.png
ConglingkaishiDeUefiLuojiBiancheng/img/apple-touch-icon.png
ConglingkaishiDeUefiLuojiBiancheng/img/cancelfullscreen.png
ConglingkaishiDeUefiLuojiBiancheng/img/close.png
ConglingkaishiDeUefiLuojiBiancheng/img/fullscreen.png
ConglingkaishiDeUefiLuojiBiancheng/img/loader.gif
ConglingkaishiDeUefiLuojiBiancheng/img/menu-icon.png
ConglingkaishiDeUefiLuojiBiancheng/img/save.png
ConglingkaishiDeUefiLuojiBiancheng/img/saved.png
ConglingkaishiDeUefiLuojiBiancheng/img/settings-s.png
ConglingkaishiDeUefiLuojiBiancheng/img/settings.png
ConglingkaishiDeUefiLuojiBiancheng/img/star.png
ConglingkaishiDeUefiLuojiBiancheng/js/__init__.py
ConglingkaishiDeUefiLuojiBiancheng/js/epub.js
ConglingkaishiDeUefiLuojiBiancheng/js/epub.min.js
ConglingkaishiDeUefiLuojiBiancheng/js/epub.min.map
ConglingkaishiDeUefiLuojiBiancheng/js/hooks.min.js
ConglingkaishiDeUefiLuojiBiancheng/js/hooks.min.map
ConglingkaishiDeUefiLuojiBiancheng/js/reader.js
ConglingkaishiDeUefiLuojiBiancheng/js/reader.js.map
ConglingkaishiDeUefiLuojiBiancheng/js/reader.min.js
conglingkaishi_de_uefi_luoji_biancheng-2024.3.5.0.dist-info/METADATA
conglingkaishi_de_uefi_luoji_biancheng-2024.3.5.0.dist-info/WHEEL
conglingkaishi_de_uefi_luoji_biancheng-2024.3.5.0.dist-info/entry_points.txt
conglingkaishi_de_uefi_luoji_biancheng-2024.3.5.0.dist-info/top_level.txt
conglingkaishi_de_uefi_luoji_biancheng-2024.3.5.0.dist-info/RECORD
